garmin_daily/__init__.py
garmin_daily/columns_mapper.py
garmin_daily/garmin_aggregations.py
garmin_daily/google_sheet.py
garmin_daily/main.py
garmin_daily/mappers.py
garmin_daily/snake_to_camel.py
garmin_daily/version.py
garmin_daily-1.4.2.dist-info/licenses/LICENSE.txt
garmin_daily-1.4.2.dist-info/METADATA
garmin_daily-1.4.2.dist-info/WHEEL
garmin_daily-1.4.2.dist-info/entry_points.txt
garmin_daily-1.4.2.dist-info/top_level.txt
garmin_daily-1.4.2.dist-info/RECORD
