Metadata-Version: 2.4
Name: garmin-daily
Version: 1.4.2
Summary: Aggregate data from Garmin Connect daily.
Home-page: https://andgineer.github.io/garmin-daily/en/
Author: Andrey Sorokin
Author-email: andrey@sorokin.engineer
Keywords: Garmin Connect Health Google Sheets
Classifier: Programming Language :: Python :: 3
Classifier: License :: OSI Approved :: MIT License
Classifier: Operating System :: OS Independent
Requires-Python: >=3.9
License-File: LICENSE.txt
Requires-Dist: requests
Requires-Dist: gspread
Requires-Dist: markdownify
Requires-Dist: click
Requires-Dist: rich-click
Requires-Dist: garminconnect
Requires-Dist: pandas
Dynamic: author
Dynamic: author-email
Dynamic: classifier
Dynamic: description
Dynamic: description-content-type
Dynamic: home-page
Dynamic: keywords
Dynamic: license-file
Dynamic: requires-dist
Dynamic: requires-python
Dynamic: summary
